{
  "UUID": "6442716a-79b2-4149-a02a-0699fe3d50c2",
  "Categoria": "",
  "Ragione Sociale": "GHEZZI MARCO GIOVANNI",
  "Indirizzo": "VIA MATTEOTTI N.50/T",
  "Sito": "http://www.ghezzioro.tk",
  "e-mail": "  desioreficeriaghezzi@libero.it",
  "Telefono": "0362 625255",
  "Facebook ID": "",
  "Facebook URL": "",
  "Google Place ID": "",
  "Google Place URL": "",
  "Latitude": "",
  "Longitude": "",
  "Categoria catastale": "N Non Domestica 15 : NEGOZI PARTICOLARI (FILATELIA-TESSUTI-ANTIQUAR.-.)"
}