{
  "UUID": "e58139dc-f6e1-406b-ba19-1dc574520537",
  "Categoria": "",
  "Ragione Sociale": "SPOT LINE SRL",
  "Indirizzo": "VIA XXV APRILE N.11",
  "Sito": "www.spotline.it",
  "e-mail": "info@spotline.it\nmike@spotline.it\nfranco@spotline.it",
  "Telefono": "0362/1793839",
  "Facebook ID": "",
  "Facebook URL": "",
  "Google Place ID": "ChIJE7YfKT28hkcRhdkqiSXqduc",
  "Google Place URL": "",
  "Latitude": "45.6197094",
  "Longitude": "9.2152146",
  "Categoria catastale": "N Non Domestica 21 : ATT. ARTIGIANALI PRODUZIONE BENI SPECIFICI",
  "formatted_address": "Via XXV Aprile, 11, 20832 Desio MB, Italy",
  "types": [
    "home_goods_store",
    "store",
    "point_of_interest",
    "establishment"
  ]
}